{"cameraMode":{"drawMode":0,"name":"Shaded","section":"Shading Mode"},"sceneLighting":true,"audioPlay":false,"sceneViewState":{"m_AlwaysRefresh":false,"showFog":true,"showSkybox":true,"showFlares":true,"showImageEffects":true,"showParticleSystems":true,"showVisualEffectGraphs":true,"m_FxEnabled":true},"in2DMode":false,"pivot":{"x":-4.991581439971924,"y":-14.204176902770996,"z":-29.474353790283204},"rotation":{"x":-0.012494456954300404,"y":-0.9482351541519165,"z":0.3152865469455719,"w":-0.037569429725408557},"size":20.920984268188478,"orthographic":false}